dedup_rs-0.1.1.dist-info/METADATA
dedup_rs-0.1.1.dist-info/WHEEL
dedup_rs-0.1.1.dist-info/license_files/LICENSE
text_dedup/ann_unisim.py
text_dedup/bloom_filter.py
text_dedup/ccnet.py
text_dedup/exact_hash.py
text_dedup/minhash.py
text_dedup/minhash_rust.py
text_dedup/minhash_spark.py
text_dedup/simhash.py
text_dedup/suffix_array.py
text_dedup/utils/analysis.py
text_dedup/utils/args.py
text_dedup/utils/const.py
text_dedup/utils/ftfy_utils.py
text_dedup/utils/hashfunc.py
text_dedup/utils/inspect.py
text_dedup/utils/load.py
text_dedup/utils/memory.py
text_dedup/utils/preprocess.py
text_dedup/utils/timer.py
text_dedup/utils/tokenization.py
text_dedup/utils/union_find.py
text_dedup/utils/__init__.py
text_dedup/__init__.py
text_dedup/dedup_rs.cp38-win32.pyd
dedup_rs-0.1.1.dist-info/RECORD
