Metadata-Version: 2.3
Name: dedup-rs
Version: 0.1.1
Classifier: Programming Language :: Rust
Classifier: Programming Language :: Python :: Implementation :: CPython
Classifier: Programming Language :: Python :: Implementation :: PyPy
Requires-Dist: numpy >=1.26.4
Requires-Dist: tqdm >=4.64.1
Requires-Dist: datasets >=2.17.0
Requires-Dist: scipy >=1.10.1
Requires-Dist: xxhash >=3.0.0
Requires-Dist: pybloom-live >=4.0.0
Requires-Dist: bitarray >=2.6.2
Requires-Dist: regex >=2023.5.5
Requires-Dist: urllib3 <=2.0
Requires-Dist: sphinxcontrib-bibtex >=2.5.0
Requires-Dist: zstandard >=0.21.0
Requires-Dist: ftfy >=6.1.1
Requires-Dist: setuptools >=69.1.0
Requires-Dist: psutil >=5.9.8
Requires-Dist: fire ~=0.6.0
Requires-Dist: click ~=8.1.7
Requires-Dist: click-option-group ~=0.5.6
Requires-Dist: rich ~=13.7.1
Requires-Dist: unisim ~=0.0.1
Requires-Dist: black ; extra == 'dev'
Requires-Dist: flake8 ; extra == 'dev'
Requires-Dist: isort ; extra == 'dev'
Requires-Dist: mypy ; extra == 'dev'
Requires-Dist: pre-commit ; extra == 'dev'
Requires-Dist: insegel ; extra == 'dev'
Requires-Dist: pytest ; extra == 'dev'
Requires-Dist: coverage ; extra == 'dev'
Requires-Dist: ruff ; extra == 'dev'
Requires-Dist: tabulate ; extra == 'dev'
Requires-Dist: scikit-learn ; extra == 'dev'
Provides-Extra: dev
License-File: LICENSE
Summary: A Rust library for deduplication of documents
Author: Wayne Lau, 
Requires-Python: >=3.8
